{
    "points": [
        {
            "x": 15.407184600830079,
            "y": 0.18562883138656617
        },
        {
            "x": 19.119762420654298,
            "y": 1.2994012832641602
        },
        {
            "x": 22.089820861816408,
            "y": 0.0
        },
        {
            "x": 26.452096939086915,
            "y": 1.9026947021484376
        },
        {
            "x": 30.257484436035158,
            "y": 7.796407222747803
        },
        {
            "x": 31.0,
            "y": 16.10329246520996
        },
        {
            "x": 28.63323402404785,
            "y": 22.878740310668947
        },
        {
            "x": 23.43562889099121,
            "y": 26.54490852355957
        },
        {
            "x": 19.908681869506837,
            "y": 25.106287002563478
        },
        {
            "x": 17.309879302978517,
            "y": 26.684131622314454
        },
        {
            "x": 16.381736755371095,
            "y": 29.422155380249025
        },
        {
            "x": 13.690119743347168,
            "y": 31.09281349182129
        },
        {
            "x": 12.06586742401123,
            "y": 29.886226654052736
        },
        {
            "x": 13.458083152770996,
            "y": 28.586824417114259
        },
        {
            "x": 14.47904109954834,
            "y": 26.73053741455078
        },
        {
            "x": 11.973052978515625,
            "y": 25.33832359313965
        },
        {
            "x": 6.032933712005615,
            "y": 26.54490852355957
        },
        {
            "x": 0.9745507836341858,
            "y": 20.32634735107422
        },
        {
            "x": 0.0,
            "y": 12.344310760498047
        },
        {
            "x": 3.109281539916992,
            "y": 3.991018295288086
        },
        {
            "x": 7.517963409423828,
            "y": 0.1392216980457306
        },
        {
            "x": 12.06586742401123,
            "y": 1.2994012832641602
        }
    ],
    "objectsNames": [
        "Cube",
        "Cube",
        "Cube"
    ],
    "objectsPositions": [
        {
            "x": 15.100000381469727,
            "y": 4.199999809265137
        },
        {
            "x": 15.100000381469727,
            "y": 13.199999809265137
        },
        {
            "x": 15.0,
            "y": 21.5
        }
    ],
    "materialName": "wood",
    "isClockWise": false
}