{
    "points": [
        {
            "x": 13.285714149475098,
            "y": 0.0
        },
        {
            "x": 13.285714149475098,
            "y": 4.4285712242126469
        },
        {
            "x": 8.857142448425293,
            "y": 4.4285712242126469
        },
        {
            "x": 8.857142448425293,
            "y": 8.857142448425293
        },
        {
            "x": 4.4285712242126469,
            "y": 8.857142448425293
        },
        {
            "x": 4.4285712242126469,
            "y": 13.285714149475098
        },
        {
            "x": 0.0,
            "y": 13.285714149475098
        },
        {
            "x": 0.0,
            "y": 17.714284896850587
        },
        {
            "x": 4.4285712242126469,
            "y": 17.714284896850587
        },
        {
            "x": 4.4285712242126469,
            "y": 22.14285659790039
        },
        {
            "x": 8.857142448425293,
            "y": 22.14285659790039
        },
        {
            "x": 8.857142448425293,
            "y": 26.571428298950197
        },
        {
            "x": 13.285714149475098,
            "y": 26.571428298950197
        },
        {
            "x": 13.285714149475098,
            "y": 31.0
        },
        {
            "x": 17.714284896850587,
            "y": 31.0
        },
        {
            "x": 17.714284896850587,
            "y": 26.571428298950197
        },
        {
            "x": 22.14285659790039,
            "y": 26.571428298950197
        },
        {
            "x": 22.14285659790039,
            "y": 22.14285659790039
        },
        {
            "x": 26.571428298950197,
            "y": 22.14285659790039
        },
        {
            "x": 26.571428298950197,
            "y": 17.714284896850587
        },
        {
            "x": 31.0,
            "y": 17.714284896850587
        },
        {
            "x": 31.0,
            "y": 13.285714149475098
        },
        {
            "x": 26.571428298950197,
            "y": 13.285714149475098
        },
        {
            "x": 26.571428298950197,
            "y": 8.857142448425293
        },
        {
            "x": 22.14285659790039,
            "y": 8.857142448425293
        },
        {
            "x": 22.14285659790039,
            "y": 4.4285712242126469
        },
        {
            "x": 17.714284896850587,
            "y": 4.4285712242126469
        },
        {
            "x": 17.714284896850587,
            "y": 0.0
        }
    ],
    "objectsNames": [
        "Cube",
        "Cube",
        "Cube"
    ],
    "objectsPositions": [
        {
            "x": 15.399999618530274,
            "y": 25.399999618530275
        },
        {
            "x": 15.300000190734864,
            "y": 5.099999904632568
        },
        {
            "x": 15.199999809265137,
            "y": 15.0
        }
    ],
    "materialName": "wood",
    "isClockWise": true
}